fruitcraft/__init__.py
fruitcraft/client.py
fruitcraft/f_types/__init__.py
fruitcraft/f_types/cards.py
fruitcraft/f_types/errors.py
fruitcraft/f_types/utils.py
fruitcraft-0.0.11.dist-info/LICENSE
fruitcraft-0.0.11.dist-info/METADATA
fruitcraft-0.0.11.dist-info/WHEEL
fruitcraft-0.0.11.dist-info/RECORD
